LICENSE
README.md
setup.py
nard_backgammon/__init__.py
nard_backgammon/board.py
nard_backgammon/exceptions.py
nard_backgammon/nard.py
nard_backgammon/player.py
nard_backgammon.egg-info/PKG-INFO
nard_backgammon.egg-info/SOURCES.txt
nard_backgammon.egg-info/dependency_links.txt
nard_backgammon.egg-info/top_level.txt