Metadata-Version: 2.1
Name: nard-backgammon
Version: 0.1.0
Summary: Classic board game of Nard (Backgammon) for two players.
Home-page: https://github.com/cmdtorch/nard-backgammon
Author: Emil Humbatov
Author-email: emil4154515@gmail.com
License: MIT
Download-URL: https://github.com/cmdtorch/nard-backgammon/archive/refs/tags/0.1.0.zip
Project-URL: Source, https://github.com/pyglet/pyglet
Project-URL: Tracker, https://github.com/pyglet/pyglet/issues
Platform: UNKNOWN
Classifier: Development Status :: 4 - Beta
Classifier: Intended Audience :: Developers
Classifier: License :: OSI Approved :: MIT License
Classifier: Operating System :: MacOS :: MacOS X
Classifier: Operating System :: Microsoft :: Windows
Classifier: Operating System :: POSIX :: Linux
Classifier: Programming Language :: Python :: 3.10
Classifier: Programming Language :: Python :: 3.11
Classifier: Topic :: Games/Entertainment :: Board Games
License-File: LICENSE
